dol/__init__.py
dol/appendable.py
dol/base.py
dol/caching.py
dol/dig.py
dol/errors.py
dol/explicit.py
dol/filesys.py
dol/kv_codecs.py
dol/misc.py
dol/mixins.py
dol/naming.py
dol/paths.py
dol/recipes.py
dol/signatures.py
dol/sources.py
dol/tools.py
dol/trans.py
dol/util.py
dol/zipfiledol.py
dol/scrap/__init__.py
dol/scrap/new_store_wrap.py
dol/scrap/store_factories.py
dol/tests/__init__.py
dol/tests/base_test.py
dol/tests/pickability_test.py
dol/tests/scrap.py
dol/tests/test_appendable.py
dol/tests/test_caching.py
dol/tests/test_dol_tools.py
dol/tests/test_edge_cases.py
dol/tests/test_fanout_stores.py
dol/tests/test_filesys.py
dol/tests/test_kv_codecs.py
dol/tests/test_paths.py
dol/tests/test_trans.py
dol/tests/utils_for_tests.py
dol-0.3.30.dist-info/licenses/LICENSE
dol-0.3.30.dist-info/METADATA
dol-0.3.30.dist-info/WHEEL
dol-0.3.30.dist-info/top_level.txt
dol-0.3.30.dist-info/RECORD
