Metadata-Version: 2.4
Name: dol
Version: 0.3.30
Summary: Base builtin tools make and transform data object layers (dols).
Home-page: https://github.com/i2mint/dol
License: mit
Keywords: storage,interface
Platform: any
License-File: LICENSE
Provides-Extra: testing
Dynamic: license-file
